launcher_links/__init__.py
launcher_links/_version.py
launcher_links-1.0.3.data/data/share/jupyter/labextensions/launcher-links/package.json
launcher_links-1.0.3.data/data/share/jupyter/labextensions/launcher-links/schemas/launcher-links/package.json.orig
launcher_links-1.0.3.data/data/share/jupyter/labextensions/launcher-links/schemas/launcher-links/plugin.json
launcher_links-1.0.3.data/data/share/jupyter/labextensions/launcher-links/static/502.2e581a23ce108cf416fa.js
launcher_links-1.0.3.data/data/share/jupyter/labextensions/launcher-links/static/509.05a0c4ed445fb697f002.js
launcher_links-1.0.3.data/data/share/jupyter/labextensions/launcher-links/static/remoteEntry.1c9c309cfaccd14c93ee.js
launcher_links-1.0.3.data/data/share/jupyter/labextensions/launcher-links/static/style.js
launcher_links-1.0.3.data/data/share/jupyter/labextensions/launcher-links/static/third-party-licenses.json
launcher_links-1.0.3.data/data/share/jupyter/labextensions/launcher-links/install.json
launcher_links-1.0.3.dist-info/METADATA
launcher_links-1.0.3.dist-info/WHEEL
launcher_links-1.0.3.dist-info/licenses/LICENSE
launcher_links-1.0.3.dist-info/RECORD
