Metadata-Version: 2.4
Name: launcher_links
Version: 1.0.3
Summary: Add abitrary launcher icons 
Project-URL: Homepage, https://github.com/bloomsa/launcher-links
Project-URL: Bug Tracker, https://github.com/bloomsa/launcher-links/issues
Project-URL: Repository, https://github.com/bloomsa/launcher-links.git
Author-email: Sam Bloomquist <bloomquist.sam@gmail.com>
License: BSD 3-Clause License
License-File: LICENSE
Keywords: jupyter,jupyterlab,jupyterlab-extension
Classifier: Framework :: Jupyter
Classifier: Framework :: Jupyter :: JupyterLab
Classifier: Framework :: Jupyter :: JupyterLab :: 4
Classifier: Framework :: Jupyter :: JupyterLab :: Extensions
Classifier: Framework :: Jupyter :: JupyterLab :: Extensions :: Prebuilt
Classifier: License :: OSI Approved :: BSD License
Classifier: Programming Language :: Python
Classifier: Programming Language :: Python :: 3
Classifier: Programming Language :: Python :: 3.9
Classifier: Programming Language :: Python :: 3.10
Classifier: Programming Language :: Python :: 3.11
Classifier: Programming Language :: Python :: 3.12
Classifier: Programming Language :: Python :: 3.13
Requires-Python: >=3.9
Requires-Dist: jupyterlab>=4.3.6
